CHANGELOG.txt
LICENSE.txt
MANIFEST.in
README.md
setup.py
bitlogs/__init__.py
bitlogs/message_type.py
bitlogs/terminal_colors.py
bitlogs.egg-info/PKG-INFO
bitlogs.egg-info/SOURCES.txt
bitlogs.egg-info/dependency_links.txt
bitlogs.egg-info/top_level.txt
bitlogs/message_types/__init__.py
bitlogs/message_types/critical_message.py
bitlogs/message_types/debug_message.py
bitlogs/message_types/error_message.py
bitlogs/message_types/info_message.py
bitlogs/message_types/warning_message.py