Metadata-Version: 2.1
Name: bitlogs
Version: 1.0.1
Summary: This python library allows you to easily create logs for your code.
Home-page: UNKNOWN
Author: Vladislav Korecký
Author-email: vladislav.ml@korecky.org
License: MIT
Keywords: bitlogs,bitlog,logs,log,logging,logger,python log
Platform: UNKNOWN
Classifier: Development Status :: 5 - Production/Stable
Classifier: Intended Audience :: Developers
Classifier: Operating System :: Microsoft :: Windows :: Windows 10
Classifier: License :: OSI Approved :: MIT License
Classifier: Programming Language :: Python :: 3
License-File: LICENSE.txt
